[{"i":0,"he":"בואו נשוט בכל ימי העולם,"},{"i":1,"he":"ונרים את קריאת הקרב שלנו."},{"i":2,"he":"אם החלטתם, תנו לאות היציאה"},{"i":3,"he":"להדהד."},{"i":4,"he":"הצלחנו לחמוק מהמסלול הקבוע"},{"i":5,"he":"לאורך הגבול שבין השמיים לים."},{"i":6,"he":"עכשיו אנחנו חותרים בדרכנו"},{"i":7,"he":"להרפתקה נסתרת במעמקי הים האפלים."},{"i":8,"he":"לא נשמע כיף רק לחשוב על זה?"},{"i":9,"he":"בואו נשוט בכל ימי העולם,"},{"i":10,"he":"ונרים את קריאת הקרב שלנו."},{"i":11,"he":"אם החלטתם, תנו לאות היציאה"},{"i":12,"he":"להדהד."},{"i":13,"he":"התחושה שהייתה לנו כשהפלגנו"},{"i":14,"he":"היא משהו שלעולם לא אשכח."},{"i":15,"he":"בזכותה"},{"i":16,"he":"שום דבר לא יוכל להפחיד אותי..."},{"i":17,"he":"עכשיו, כשהמסע מתקרב, פעימות הלב הדוהרות שלנו"},{"i":18,"he":"חורטות קצב של הרפתקה\\Nבלבבותינו הביישנים."},{"i":19,"he":"אספו את כל האוצרות"},{"i":20,"he":"תוך צחוק בקול רם."},{"i":21,"he":"תנו את הכל במסיבה גדולה"},{"i":22,"he":"ועשו רעש..."},{"i":23,"he":"מלאו את לבכם הריק בחלומות."},{"i":24,"he":"פרשו כנפיים."},{"i":25,"he":"אם תצבעו את לבכם ברוח הנושבת"},{"i":26,"he":"תמשיכו הלאה."},{"i":27,"he":"אספו את כל האוצרות"},{"i":28,"he":"תוך צחוק בקול רם."},{"i":29,"he":"תנו את הכל במסיבה גדולה"},{"i":30,"he":"ועשו רעש..."},{"i":31,"he":"היכולת המפחידה של פרי הצל!\\Nהמספר 900 האולטימטיבי!"},{"i":32,"he":"זה לא נגמר!"},{"i":33,"he":"למרות שחתכתי אותו, הוא עדיין זומבי."},{"i":34,"he":"הוא ימשיך לקום!"},{"i":35,"he":"אתה...!"},{"i":36,"he":"רגע אחד... ראיתי אותך כבר..."},{"i":37,"he":"אל תדאג."},{"i":38,"he":"כבר חיסלתי אותו."},{"i":39,"he":"חיסלת?"},{"i":40,"he":"לזומבים האלה יש נקודת תורפה."},{"i":41,"he":"מה היא?!"},{"i":42,"he":"זו הנשמה של הזומבי."},{"i":43,"he":"נשמה?"},{"i":44,"he":"היא יוצאת ממש מול העיניים שלנו!"},{"i":45,"he":"עכשיו, חזרי לאדון שלך!"},{"i":46,"he":"מפקד טאראראן!"},{"i":47,"he":"המפקד הובס!"},{"i":48,"he":"הוא הפסיק לזוז לגמרי."},{"i":49,"he":"מה עשית?!"},{"i":50,"he":"טיהור."},{"i":51,"he":"תראו!"},{"i":52,"he":"אין ספק, זה ה\"מזמזם\"."},{"i":53,"he":"זה האיש שעורר מהומה בת'רילר בארק\\Nלפני חמש שנים."},{"i":54,"he":"תדווחו לאדון!"},{"i":55,"he":"קורי העכביש האלה אכן חזקים\\Nבפני כוח פיזי, אבל עדיין חלשים מול אש."},{"i":56,"he":"אתה צודק!"},{"i":57,"he":"זה נמס!"},{"i":58,"he":"כובע הקש והאחרים נחטפו."},{"i":59,"he":"נראה שאתה יודע די הרבה על האי הזה."},{"i":60,"he":"כן."},{"i":61,"he":"אבל, אני לא ממש בטוח איך לנסח את זה."},{"i":62,"he":"העובדה שהם נתפסו אומרת\\Nשיש סיכוי גבוה שכבר מאוחר מדי."},{"i":63,"he":"מה?!"},{"i":64,"he":"מאוחר מדי?!"},{"i":65,"he":"ב-בבקשה אל תכעס עלי."},{"i":66,"he":"בוא נשמור על פרצוף רציני!"},{"i":67,"he":"אפילו שכשלד, אין לי פרצוף!"},{"i":68,"he":"בדיחת גולגולת!"},{"i":69,"he":"תפסיק, הוא כבר מת."},{"i":70,"he":"בכל אופן,"},{"i":71,"he":"תפסיק להתבדח ותקשיב לי."},{"i":72,"he":"תפסיק, הוא כבר מת."},{"i":73,"he":"זה כמו שסיפרתי לכם על הספינה,\\Nכשההגה של הספינה שלי התקלקל,"},{"i":74,"he":"התחלתי לשוטט בים לבד לפני עשרות שנים..."},{"i":75,"he":"חשבתי לברוח מהים המרושע הזה,\\Nאבל עם ההגה השבור הייתי רק בובה של הזרם."},{"i":76,"he":"זה היה לפני יותר מחמש שנים."},{"i":77,"he":"וממש כמוכם עכשיו,\\Nבסוף הובלתי לת'רילר בארק."},{"i":78,"he":"רציתי לעזוב את משולש פלוריאן\\Nלא משנה מה."},{"i":79,"he":"בתקווה שאולי יהיו חלקים לתיקון ההגה\\Nבאי, חקרתי."},{"i":80,"he":"כשנכנסתי, מצאתי רק זומבים\\Nומפלצות בדרך."},{"i":81,"he":"תוך זמן קצר נתפסתי\\Nוהובאתי לבניין הזה."},{"i":82,"he":"בפנים ראיתי רקדן קרב שנתפס קודם\\Nוגופה מטולאת שקראו לה מריונטה."},{"i":83,"he":"אחר כך הופיע איש ענק ומפחיד, ו...!"},{"i":84,"he":"הוא תלש את הצל של האיש מהרצפה!"},{"i":85,"he":"הוא חתך אותו!"},{"i":86,"he":"הצל שלו נחתך?"},{"i":87,"he":"חשבתי שהעיניים שלי מטעות אותי...\\Nאפילו ש..."},{"i":88,"he":"אין לי בכלל עיניים."},{"i":89,"he":"תפסיק להתבדח או שאני אבעט לך בתחת!"},{"i":90,"he":"לא אכפת לי אם תעשה את זה."},{"i":91,"he":"עמד לי לקרות אותו גורל בקרוב."},{"i":92,"he":"זה שהצל שלו נלקח קרס במקום שעמד בו."},{"i":93,"he":"מצד שני, הצל הכרות שלו נדחק\\Nאל תוך הגוף הדומם של המריונטה."},{"i":94,"he":"לא חשבתי שזה אפשרי..."},{"i":95,"he":"איך הוא עשה את זה, אני לא בטוח..."},{"i":96,"he":"אבל, גופת המריונטה פשוט..."},{"i":97,"he":"התחילה לזוז מעצמה!"},{"i":98,"he":"למה אתה מתכוון?"},{"i":99,"he":"צל הוא נשמה נוספת\\Nשהולכת וזזה איתך לכל מקום."},{"i":100,"he":"הוא נלווה אליך מהלידה ועד המוות."},{"i":101,"he":"זו נשמה שלעולם לא תעזוב אותך,\\Nשתמיד תציית ותלך אחריך."},{"i":102,"he":"האיש שתופס את אלה,\\Nומכריח אותם לציית לרצונו הוא..."},{"i":103,"he":"לוחם הים המלכותי, גקו מוריה!"},{"i":104,"he":"המשתמש בפרי הצל."},{"i":105,"he":"פרי שטן, הא?"},{"i":106,"he":"כל עוד יש גופה,\\Nהוא יכול להשתמש בצל כדי ליצור זומבי."},{"i":107,"he":"הבעיה היא שלמנתח הגאון שיוצר את היצורים\\Nהקשוחים האלה, ד\"ר הוגבק... יש חברים."},{"i":108,"he":"במקרים מסוימים, הוא משיג חלקים\\Nמבתי קברות שונים..."},{"i":109,"he":"ומשתמש בגופות של לוחמים אגדיים\\Nכדי להחיות אותם."},{"i":110,"he":"יתרה מזאת, יש לו כמות עצומה של מריונטות\\Nממוספרות שעדיין מאוחסנות במקפיא במעבדה שלו."},{"i":111,"he":"ד\"ר הוגבק..."},{"i":112,"he":"אז הרופא המפורסם הזה בא לכאן\\Nאחרי אירוע ההיעלמות שלו כדי לעזור לפיראט."},{"i":113,"he":"אז, הגופות של הזומבים יכולות לזוז,\\Nאז זה לא שהם הוקמו לתחייה."},{"i":114,"he":"נכון."},{"i":115,"he":"הצל מחזיק גם את האישיות\\Nוגם את כישורי הלחימה של בעליו."},{"i":116,"he":"הכוח הפיזי של המריונטה\\Nמוגבל על ידי עוצמת הגוף שלה."},{"i":117,"he":"כששילוב של צל חזק וגוף חזק מתאחד,\\Nהתוצאה היא זומבי חזק עוד יותר."},{"i":118,"he":"בגלל זה מוריה כל כך משתוקק\\Nלצללים של ראשים מבוקשים."},{"i":119,"he":"אני מבין."},{"i":120,"he":"הם רדפו אחרינו מההתחלה."},{"i":121,"he":"אז זה כל הסיפור של ת'רילר בארק."},{"i":122,"he":"בשביל מוריה, התכונה הכי חשובה\\Nשל זומבי היא כנראה צייתנות."},{"i":123,"he":"ככל שהלוחם חזק יותר,\\Nכך בטח קשה יותר לגרום לו לציית."},{"i":124,"he":"נכון... הם מקבלים את אותה רוח לחימה\\Nואת אותו כישרון כמו בעליהם."},{"i":125,"he":"את החזקים משלחים לסחף בים\\Nאחרי שהם מאבדים את ההכרה."},{"i":126,"he":"אז, הם...!"},{"i":127,"he":"זה לא טוב."},{"i":128,"he":"הם עדיין בטוחים."},{"i":129,"he":"יש לנו זמן."},{"i":130,"he":"עכשיו אספר לכם\\Nאת התוכנית הכי טובה שיש לנו."},{"i":131,"he":"אז בבקשה, תבטחו בי ותעשו מה שאומר."},{"i":132,"he":"לבטוח בך?!"},{"i":133,"he":"הלם גולגולת!"},{"i":134,"he":"לא ניהלתי שיחה כזו כבר עשרות שנים!\\Nזה כל כך כיף!"},{"i":135,"he":"אנחנו מקשיבים, אז ספר לנו מהר."},{"i":136,"he":"אוקי..."},{"i":137,"he":"אדון!"},{"i":138,"he":"שלושת האנשים המסתוריים הגיעו!"},{"i":139,"he":"זה היה מהיר. תכניסו."},{"i":140,"he":"בבקשה, היכנסו."},{"i":141,"he":"סוף סוף הגעת."},{"i":142,"he":"תהפוך אותי למלך הפיראטים."},{"i":143,"he":"בקרוב מאוד."},{"i":144,"he":"אתה לא מלך הפיראטים!"},{"i":145,"he":"מלך הפיראטים יהיה..."},{"i":146,"he":"אני!"},{"i":147,"he":"היי! תתיר את החוט הזה, חזרת ענק!"},{"i":148,"he":"אוסופ, נאמי, צ'ופר, סאנג'י, זורו...\\Nתחזיר את כולם!"},{"i":149,"he":"לאן לקחת אותם, חזרת?!"},{"i":150,"he":"איזה איש חזק להפליא."},{"i":151,"he":"אז זה כובע הקש לופי."},{"i":152,"he":"היי, כובע הקש לופי."},{"i":153,"he":"הזכרת הרבה שמות."},{"i":154,"he":"עד עכשיו תפסנו רק שלושה מכם."},{"i":155,"he":"צייד הפיראטים זורו\\Nובחור בלונדיני בלי מודעת מבוקש."},{"i":156,"he":"יכול להיות שהבחור הבלונדיני הוא סאנג'י...?"},{"i":157,"he":"מה?!"},{"i":158,"he":"היי, נראה שגם זורו וסאנג'י נתפסו."},{"i":159,"he":"אין מצב, וגם לופי נתפס!"},{"i":160,"he":"א-איך השלישייה המפלצתית הזו\\Nנתפסה כל כך בקלות?!"},{"i":161,"he":"אני לא יודע מי החבר'ה האלה,\\Nאבל הם בהחלט בשורות רעות!"},{"i":162,"he":"אגב, מה קרה עם השלושה האלה, פרונה?"},{"i":163,"he":"האחים המסוכנים היו אמורים\\Nלהביא אותם..."},{"i":164,"he":"הם לא הביאו אותם לקומאשי."},{"i":165,"he":"הם לא ברחו בזמן שהובילו אותם?"},{"i":166,"he":"הם מדברים עלינו."},{"i":167,"he":"אל תגיד את זה. אתה... אל תגיד את זה!"},{"i":168,"he":"אמרתי לך לא לפתוח את הפה!"},{"i":169,"he":"את קשוחה מדי עם קומאשי..."},{"i":170,"he":"קשוחה מדי."},{"i":171,"he":"בכל אופן, ניסיתי להשיג את הכלה שלי\\Nכששלושת אלה..."},{"i":172,"he":"התפרצו לגן שלך ועוררו מהומה."},{"i":173,"he":"היי, רגע אחד."},{"i":174,"he":"זה אומר... הוגבק...!"},{"i":175,"he":"מנוול, אתה מתכוון שאחד מכם\\Nשלח יד בכלה שלי?!"},{"i":176,"he":"אז זה מה שקרה קודם!"},{"i":177,"he":"הכלה שלך לא באה."},{"i":178,"he":"מה זה היה, סינדרי?!"},{"i":179,"he":"היי! היי! סינדרי-צ'אן,\\Nאת רק מחמירה את המצב!"},{"i":180,"he":"ולמה יצאת ועמדת מולי?"},{"i":181,"he":"גם שלך לא תבוא."},{"i":182,"he":"איזו מהלומה נמוכה!\\Nמאיפה זה הגיע?!"},{"i":183,"he":"די! די!"},{"i":184,"he":"תפסיקו עם הוויכוח חסר התועלת הזה."},{"i":185,"he":"אם כמה פיראטים ברחו,\\Nאז אתם יכולים לטפל בזה אחר כך."},{"i":186,"he":"אספתי אתכם לכאן כדי לחגוג\\Nאת יצירתו של נכס לחימה אדיר."},{"i":187,"he":"מי הבחור הזה?!"},{"i":188,"he":"אדון, הפיראט הזה\\Nנשך וקרע את הכלוב כדי לברוח!"},{"i":189,"he":"הוא...!"},{"i":190,"he":"נשך את הכלוב!"},{"i":191,"he":"מה אתה הולך לעשות כדי לתפוס אותי עכשיו?!"},{"i":192,"he":"איזה איש מבטיח!"},{"i":193,"he":"רגע, אבסלום, אנחנו בתוך חדר."},{"i":194,"he":"אני אעצור אותו."},{"i":195,"he":"כאילו שתתפסי אותי, אידיוטית!"},{"i":196,"he":"{\\fad(150,150)}חלל שלילי!"},{"i":197,"he":"אם אהיה נולד מחדש,\\Nאני רוצה להיות חשופית ים..."},{"i":198,"he":"האיש שהרגע אמר שהוא רוצה להיות\\Nמלך הפיראטים עכשיו רוצה להיות חשופית ים..."},{"i":199,"he":"נורא..."},{"i":200,"he":"תדליקו את האור!"},{"i":201,"he":"מה אתה עושה, לעזאזל!"},{"i":202,"he":"אתה תתחרט על זה!"},{"i":203,"he":"מ-מה זה?!"},{"i":204,"he":"הצל שלי...!"},{"i":205,"he":"סוף סוף הוא שלי!"},{"i":206,"he":"300 המיליון עוצמת לחימה!"},{"i":207,"he":"עם זה, אפשר ליצור\\Nאת הזומבי המיוחד האולטימטיבי!"},{"i":208,"he":"לחזור לספינה?"},{"i":209,"he":"לסאני?"},{"i":210,"he":"נכון."},{"i":211,"he":"התרחיש הגרוע ביותר הוא\\Nשהחברים שלכם נתפסו והצללים שלהם נגנבו."},{"i":212,"he":"אבל, גניבת הצל שלהם לא תהרוג אותם."},{"i":213,"he":"תסתכלו מה קרה לי!"},{"i":214,"he":"אה, מתי!"},{"i":215,"he":"זה סיפור אחר לגמרי!"},{"i":216,"he":"בכל אופן..."},{"i":217,"he":"בקיצור, גם אם הצל שלהם נגנב,\\Nהם לא ימותו."},{"i":218,"he":"נכון."},{"i":219,"he":"אבל, ברגע שהצללים שלהם נלקחים,\\Nהם נעשים פגיעים כשהם מאבדים את ההכרה."},{"i":220,"he":"ולא יתעוררו במשך יומיים."},{"i":221,"he":"בזמן הזה הם מכניסים את החזקים\\Nלסירות ומשלחים אותם מת'רילר בארק."},{"i":222,"he":"אמרתי את זה כבר, אבל\\Nאתם יודעים למה הם עושים את זה?"},{"i":223,"he":"כדי שהקורבנות לא ינסו לחזור לאי\\Nולקחת בחזרה את הצללים שלהם, נכון?"},{"i":224,"he":"בדיוק."},{"i":225,"he":"אז, למה שלא פשוט יהרגו אותם\\Nכשהם מחוסרי הכרה?"},{"i":226,"he":"הם לא יכולים."},{"i":227,"he":"זה מאוד חשוב, אז תקשיבו טוב."},{"i":228,"he":"קודם כל..."},{"i":229,"he":"למרות שהגוף והצל עשויים להיות מופרדים,\\Nהם חלק מישות אחת."},{"i":230,"he":"אם הגוף מת, אז גם הצל נידון."},{"i":231,"he":"במילים אחרות, ברגע שזה קורה,\\Nגם הזומבי יכלה."},{"i":232,"he":"זו צרה עבור האויב,\\Nאז הם מקפידים לשמור את הגוף בחיים."},{"i":233,"he":"מה שאומר שאפילו אם הצללים\\Nשל החברים שלכם נשללו..."},{"i":234,"he":"הם בוודאות בחיים\\Nומובלים בחזרה לספינה."},{"i":235,"he":"בגלל זה...!"},{"i":236,"he":"אם גם שניכם תיהפכו לקורבנות,\\Nזה יהפוך לתרחיש הגרוע ביותר!"},{"i":237,"he":"כולם יאבדו את הצללים שלהם\\Nויישארו לשוטט בים."},{"i":238,"he":"אבל עדיין אפשר לעשות משהו.\\Nאם נעיר את החברים שלכם..."},{"i":239,"he":"תהיה לנו הזדמנות אחת להבין\\Nאיך להחזיר את הצללים הגנובים."},{"i":240,"he":"הבנתם את כל זה?"},{"i":241,"he":"אני מבין."},{"i":242,"he":"זה הגיוני."},{"i":243,"he":"קחו את זה, שניכם."},{"i":244,"he":"מה זה?"},{"i":245,"he":"נקודת התורפה של הזומבים."},{"i":246,"he":"היעילות שלו נגד קוף העכביש היא ההוכחה!"},{"i":247,"he":"נקודת תורפה?"},{"i":248,"he":"מה זה?"},{"i":249,"he":"מלח."},{"i":250,"he":"מלח?"},{"i":251,"he":"אז זה קצת כמו שאנחנו מביסים\\Nיצור רשע על ידי טיהור שלו?"},{"i":252,"he":"טוב, אפשר להגיד את זה."},{"i":253,"he":"הזומבים מונעים במקור\\Nעל ידי כוח פרי השטן."},{"i":254,"he":"ממש כמו שהים מבטל\\Nאת היכולות של משתמש בפרי שטן..."},{"i":255,"he":"המלח שיש בו את כוח הים\\Nמפרק את הקשר בין הנשמה המזויפת לגופה."},{"i":256,"he":"אני מבין."},{"i":257,"he":"אז הדבר ההוא שעף מהפה של הקוף\\Nלפני רגע היה הצל מתוך הגוף שלו."},{"i":258,"he":"לחשוב שהייתה להם נקודת תורפה כזו..."},{"i":259,"he":"עכשיו, כדי להביס את הזומבים,\\Nפשוט תזרקו את המלח לתוך הפה שלהם!"},{"i":260,"he":"זה הטריק!"},{"i":261,"he":"הטריק היחיד!"},{"i":262,"he":"הטריק!"},{"i":263,"he":"הטריק, הטריק, הטריק!"},{"i":264,"he":"אבל ברוק..."},{"i":265,"he":"איך זה שאתה יודע כל כך הרבה\\Nעל האי הזה ועל הזומבים?"},{"i":266,"he":"כשהצל שלי נגנב לפני חמש שנים..."},{"i":267,"he":"כמובן ששולחתי בספינה שלי, אבל למרבה המזל\\Nהתעוררתי בזמן ומצאתי דרך לחזור."},{"i":268,"he":"ואז חזרתי לאי..."},{"i":269,"he":"כדי להלחם..."},{"i":270,"he":"בזומבי שיש לו את הצל שלי!"},{"i":271,"he":"אבל... הובסתי לחלוטין."},{"i":272,"he":"ברחתי בבושת פנים כדי להציל את חיי..."},{"i":273,"he":"לא משנה מה..."},{"i":274,"he":"לא משנה מה... לא רציתי למות."},{"i":275,"he":"כי הייתי הניצול היחיד מהספינה שלי."},{"i":276,"he":"כי הבטחתי לחברים שלי\\Nשיום אחד אברח מים השטן הזה..."},{"i":277,"he":"ברחתי בבושת פנים כדי להציל את חיי!"},{"i":278,"he":"ולמרות שהצלחתי לחיות זמן רב,\\Nלא הצלחתי להגיע לשום פתרון."},{"i":279,"he":"בגלל זה... הפעם אני לא אברח!"},{"i":280,"he":"עד שאני אביס את האיש הזה\\Nואחזיר את הצל שלי אני-"},{"i":281,"he":"ובכן..."},{"i":282,"he":"סלחו לי, אני אלך ראשון."},{"i":283,"he":"שיהיה לכם יום טוב."},{"i":284,"he":"רגע אחד!"},{"i":285,"he":"כל עוד אנחנו עוד כאן,\\Nרק תענה לי על עוד שאלה אחת."},{"i":286,"he":"ל-לופי!"},{"i":287,"he":"מה זה היה... הרגע?"},{"i":288,"he":"הצל שלו...!"},{"i":289,"he":"הצל שלו נתלש!"},{"i":290,"he":"זה בדיוק כמו הסיפור\\Nשהשלד ברוק סיפר לנו."},{"i":291,"he":"אם הצל שלו נלקח...\\Nאז זה אומר שהבחור הזה לקח גם את של ברוק!"},{"i":292,"he":"אני לא מאמין..."},{"i":293,"he":"איך הוא יכול לעשות דבר כזה?"},{"i":294,"he":"קומאשי! שוב פטפטת, נכון?!"},{"i":295,"he":"את קשוחה מדי עם קומאשי..."},{"i":296,"he":"קשוחה מדי."},{"i":297,"he":"הבחור הזה יקרב אותי צעד אחד\\Nלהיות מלך הפיראטים, נכון הוגבק?"},{"i":298,"he":"מהיום שפגשתי אותך לפני עשר שנים,\\Nשירתתי אותך למען היום שבו ייווצר מספר 900."},{"i":299,"he":"עם הצל הזה נוכל ליצור\\Nאת הזומבי הגדול ביותר שאי פעם נוצר..."},{"i":300,"he":"ובלי ספק, הוא ייהפך\\Nלמקור כוח עצום עבורנו!"},{"i":301,"he":"היום שבו אהיה ידוע בכל העולם\\Nכמלך בית הקברות התקרב!"},{"i":302,"he":"ממלכת חלומותי שבה כל יצורי החמד בעולם\\Nייהפכו לזומבים שישרתו אותי כבר מול עיני!"},{"i":303,"he":"אפילו המנוול הכי חצוף ייהפך\\Nלזומבי צייתן אם אקח את הצל שלו!"},{"i":304,"he":"אהפוך את העולם הזה\\Nלעולם מלא בזומבים צייתנים!"},{"i":305,"he":"אם היה לי משרת כזה אז..."},{"i":306,"he":"לא הייתי מפסיד לאידיוט הזה\\Nקאידו בעולם החדש!"},{"i":307,"he":"בואו נעיר אותו כבר!"},{"i":308,"he":"גיורו!"},{"i":309,"he":"נין!"},{"i":310,"he":"באו!"},{"i":311,"he":"כן, אדון!"},{"i":312,"he":"פתחו את הדלת למקפיא המיוחד!"},{"i":313,"he":"מיד, אדון!"},{"i":314,"he":"רק תחכה, 900."},{"i":315,"he":"עכבר עכביש."},{"i":316,"he":"תזרוק את הגוף של כובע הקש לופי\\Nלספינה שלו."},{"i":317,"he":"ואל תשכח להסיר את החוט,\\Nזו תהיה צרה אם הוא ימות."},{"i":318,"he":"כן!"},{"i":319,"he":"בבקשה חכה! יש לי דיווח!"},{"i":320,"he":"מה יש?"},{"i":321,"he":"הרגע, מפקד קוף העכביש טאראראן הובס!"},{"i":322,"he":"הובס?"},{"i":323,"he":"זה לא אפשרי, אלא אם הצל שלו חולץ."},{"i":324,"he":"הצל שלו חולץ!"},{"i":325,"he":"אבסלום..."},{"i":326,"he":"האיש היחיד שמסוגל לדבר כזה, הוא הוא!"},{"i":327,"he":"סייף המזמזם האבירי!"},{"i":328,"he":"נראה שהדיווח שהילדון נתן לי\\Nלא היה שגוי."},{"i":329,"he":"זה נורא!"},{"i":330,"he":"ה\"מזמזם\" משחרר המון צללים!"},{"i":331,"he":"לפני שהבנתי, היו אינספור קורבנות!"},{"i":332,"he":"בקצב הזה, הסיוט מלפני חמש שנים\\Nיחזור על עצמו!"},{"i":333,"he":"לעזאזל... הוא האיש היחיד שיכול\\Nלגלות את נקודת התורפה של הזומ-"},{"i":334,"he":"הא?"},{"i":335,"he":"איך הוא גילה-"},{"i":336,"he":"סינדרי-צ'אן, למה את עומדת מולי?!"},{"i":337,"he":"שמעתי עליו אבל... איך הוא נראה?"},{"i":338,"he":"פרונה, את לא יודעת איך הוא נראה?"},{"i":339,"he":"אז, לכן הוא לא זוהה."},{"i":340,"he":"אדון!"},{"i":341,"he":"מחולל הצרות הזה הגיע שוב..."},{"i":342,"he":"כאילו שאכפת לי מדבר כזה, אידיוט!"},{"i":343,"he":"אתה תטפל בזה!"},{"i":344,"he":"ר-רגע!"},{"i":345,"he":"עכשיו, אל המקפיא."},{"i":346,"he":"בכל זאת, המצב הנוכחי הוא..."},{"i":347,"he":"אידיוט! תגיד את זה מההתחלה!"},{"i":348,"he":"במקרה הזה, אנחנו אמורים\\Nלהיות מסוגלים לעצור אותו."},{"i":349,"he":"כן."},{"i":350,"he":"אם תהיה בעיה כשהוא מתעורר, תדווח."},{"i":351,"he":"עכשיו זוז וזרוק כבר את כובע הקש."},{"i":352,"he":"כן!"},{"i":353,"he":"הופ!"},{"i":354,"he":"אידיוט, אל תצא!"},{"i":355,"he":"נראה שמלשלול ממך את הצל לא יהרוג אותך!"},{"i":356,"he":"זה לא הרג את ברוק."},{"i":357,"he":"אנחנו לא יכולים לצאת עדיין."},{"i":358,"he":"נחכה להזדמנות שלנו!"},{"i":359,"he":"נראה שהם הולכים לעשות משהו\\Nעם הצל של לופי."},{"i":360,"he":"אנחנו צריכים לראות מה קורה לו\\Nכדי שנוכל להחזיר אותו אחר כך!"},{"i":361,"he":"השניים האלה כבר לא כאן."},{"i":362,"he":"לאן הם הלכו?"},{"i":363,"he":"אני לא מאמין שהם הביסו את טאראראן."},{"i":364,"he":"איפה האויב?!"},{"i":365,"he":"אני אחתוך אותם ברגע!"},{"i":366,"he":"פרנקי."},{"i":367,"he":"מה את רוצה?! אני לא בוכה!"},{"i":368,"he":"אידיוטית, אל תסתכלי לכאן!"},{"i":369,"he":"למה שאלת אותו... שאלה כזו?"},{"i":370,"he":"שתקי! אל תשימי לב אלי!"},{"i":371,"he":"לעזאזל! אני אוהב את השלד הזה עכשיו!"},{"i":372,"he":"אין בחור טוב כמוהו בשום מקום!"},{"i":373,"he":"לעזאזל!"},{"i":374,"he":"אתה צודק."},{"i":375,"he":"כמו שחשבתי, אתה לא הולך לוותר\\Nרק כי בעטו בך החוצה."},{"i":376,"he":"כמובן!"},{"i":377,"he":"אתה לא יודע את שמי?"},{"i":378,"he":"כל מי ששומע את השם\\Nאמן הסיף ריומה יירתע מפחד."},{"i":379,"he":"שתוק!"},{"i":380,"he":"אתה הצל שלי!"},{"i":381,"he":"יש הבדל גדול בין הגופים שלנו."},{"i":382,"he":"אתה תחזור..."},{"i":383,"he":"אל הרגליים שלי!"},{"i":384,"he":"אני לא יכול לחכות!"},{"i":385,"he":"כשראיתי את הגופה שלו בארץ הקרח,\\Nלא יכולתי שלא לרעוד."},{"i":386,"he":"עוצר לי את הנשימה לחשוב שהיצור\\Nהדוחה הזה השתולל בימים לפני 500 שנה!"},{"i":387,"he":"הוא לקח את כל האי\\Nשל כל ארץ שכבש כדי להרחיב את שטחו..."},{"i":388,"he":"קר...!"},{"i":389,"he":"וכך הוא בנה את מה שקרוי ארץ הרשע."},{"i":390,"he":"מייסד אגדת מושך-הארצות עצמו נמצא שם!"},{"i":391,"he":"זה יהיה הזומבי הכי טוב שאי פעם נוצ-"},{"i":392,"he":"האגדה תיוולד מחדש שוב!"},{"i":393,"he":"עכשיו... הגיע הזמן להקים לתחייה...!"},{"i":394,"he":"את האיש היחיד בהיסטוריה...!"},{"i":395,"he":"הלוחם הפראי שכונה השד!"},{"i":396,"he":"אורס!"}]